hzdatasdk/__init__.py
hzdatasdk/api.py
hzdatasdk/choice.py
hzdatasdk/choiceinfo.py
hzdatasdk/client.py
hzdatasdk/hz_finance_service.py
hzdatasdk/hzdata_pb2.py
hzdatasdk/hzdata_pb2_grpc.py
hzdatasdk/utils.py
hzdatasdk-1.1.0.dist-info/LICENSE
hzdatasdk-1.1.0.dist-info/METADATA
hzdatasdk-1.1.0.dist-info/WHEEL
hzdatasdk-1.1.0.dist-info/top_level.txt
hzdatasdk-1.1.0.dist-info/RECORD
