Metadata-Version: 2.1
Name: hzdatasdk
Version: 1.1.0
Summary: shanghai hz finance data sdk
Home-page: https://github.com/pypa/hzdatasdk
Author: hz finance
Author-email: author@example.com
Project-URL: Bug Tracker, https://github.com/pypa/hzdatasdk/issues
Classifier: Programming Language :: Python :: 3
Classifier: License :: OSI Approved :: MIT License
Classifier: Operating System :: OS Independent
Requires-Python: >=3.7
License-File: LICENSE
Requires-Dist: six
Requires-Dist: pandas>=1.3.5
Requires-Dist: msgpack
Requires-Dist: sqlalchemy
Requires-Dist: grpcio
Requires-Dist: protobuf
